{
	"abb.note.quantiser" : {
		"patcher" : "abb.note.quantiser",
		"type" : "note",
		"block_ui_patcher" : "example.mini.ui",
		"ui_in_sidebar_height" : 1,		
		"no_edit" : 1,
		"help_text" : "Quantiser (needs Scale Master)",
		"max_polyphony" : 1,
		"connections" : {
			"in" : {
				"midi" : [ "note in" ]
			},
			"out" : {
				"midi" : [ "quantised note out" ]
			}
		},
		"groups" : [
			{
				"contains" : [7, 8, 13, 14]

			},
			{ 
				"contains" : [0, 1, 2, 3, 4, 5, 6],
				"header"	: "Scale Degrees",
				"height" : 0
			},
			{
				"contains"	:[9, 10, 11, 12, 15],
				"header"	:"Modify"
			}
		],
		"panel" : {
			"parameters" : [0, 1, 2, 3, 4, 5, 6]
		},
		"parameters" : [
			{
				"name" : "Ton",
				"type" : "menu_b",
				"values" : ["0", "1"],
				"colours" : [ [50,40,70] , 40 ],
				"wrap" : 0,
				"default" : 1
			},
			{
				"name" : "SubT",
				"type" : "menu_b",
				"values" : ["0", "1"],
				"colours" : [ [50,20,20], 30 ],
				"wrap" : 0,
				"default" : 1
			},
			{
				"name" : "Med",
				"type" : "menu_b",
				"values" : ["0", "1"],
				"colours" : [ [50,20,20], 30 ],
				"wrap" : 0,
				"default" : 1
			},
			{
				"name" : "SDom",
				"type" : "menu_b",
				"values" : ["0", "1"],
				"colours" : [ [50,20,20], 30 ],
				"wrap" : 0,
				"default" : 1
			},
			{
				"name" : "Dom",
				"type" : "menu_b",
				"values" : ["0", "1"],
				"colours" : [ [50,20,20], 30 ],
				"wrap" : 0,
				"default" : 1
			},
			{
				"name" : "SMed",
				"type" : "menu_b",
				"values" : ["0", "1"],
				"colours" : [ [50,20,20], 30 ],
				"wrap" : 0,
				"default" : 1
			},
			{
				"name" : "LNot",
				"type" : "menu_b",
				"values" : ["0", "1"],
				"colours" : [ [50,20,20], 30 ],
				"wrap" : 0,
				"default" : 1
			},
			{
				"name" : "Shift",
				"type"	: "int",
				"values" : ["uni", -14, 14, "lin"],
				"wrap" : 0,
				"default" : 0.5
			},
			{
				"name" : "Octave",
				"type"	: "int",
				"values" : ["uni", -2, 2, "lin"],
				"wrap" : 0,
				"default" : 0.5
			},
			{
				"name" : "Gap",
				"type"	: "int",
				"values" : ["uni", 1, 23, "lin"],
				"wrap" : 0,
				"default" : 0
			},
			{
				"name" : "Limit",
				"type"	: "int",
				"values" : ["uni", 1, 17, "lin"],
				"wrap" : 0,
				"default" : 0
			},
			{
				"name" : "Size",
				"type"	: "int",
				"values" : ["uni", 1, 16, "lin"],
				"wrap" : 0,
				"default" : 0
			},
			{
				"name" : "Up/Down",
				"type"	: "int",
				"values" : ["uni", 0, 1, "lin"],
				"wrap" : 0,
				"default" : 0
			},
			{
				"name" : "Length",
				"type"	: "int",
				"values" : ["uni", 10, 1000, "lin"],
				"wrap" : 0,
				"default" : 0
			},
			{
				"name" : "(friend)",
				"type"	: "int",
				"values" : ["uni", 0, 14, "lin"],
				"wrap" : 0,
				"default" : 0
			},
			{
				"name" : "Bar Reset",
				"type"	: "int",
				"values" : ["uni", 0, 8, "lin"],
				"wrap" : 0,
				"default" : 0
			}
		]
	}
}