{
	"fx.reverb.abl.darkhall" : {
		"patcher" : "fx.reverb.abl.darkhall",
		"type" : "audio",
		"block_ui_patcher" : "blank.ui",
		"help_text" : "wrapper for the abl.dsp.darkhall reverb. stereo in stereo out. only available in max 9.",
		"max_polyphony" : 0,
		"upsample" : 1,
		"subvoices" : 2,
		"connections" : {
			"in" : { 
				"audio" : [ "in" ]
			},
			"out" : {
				"audio" : [ "out" ]
			}
		},
		"groups" : [
			{ 
				"contains" : [0,1,2,3,4],
				"height" : 3
			},
			{ 
				"contains" : [5,6,7,8],
				"height" : 2
			}				
		],
		"parameters" : [
			{
				"name" : "damping",
				"type" : "float",
				"values" : ["uni", 0, 1, "lin"],
				"wrap" : 0,
				"default" : 0.5
			},
			{
				"name" : "size",
				"type" : "float",
				"values" : ["uni", 0, 1, "lin"],
				"wrap" : 0,
				"default" : 0.5
			},
			{
				"name" : "decay",
				"type" : "float",
				"values" : ["uni", 0.1, 60, "exp10"],
				"wrap" : 0,
				"default" : 0.25
			},
			{
				"name" : "shape",
				"type" : "float",
				"values" : ["uni", 0, 1, "lin"],
				"wrap" : 0,
				"default" : 0.5
			},
			{
				"name" : "freeze",
				"force_label" : 1,
				"type" : "menu_b",
				"values" : ["off", "on"],
				"wrap" : 0,
				"default" : 0.25
			},
			{
				"name" : "bass_crossover",
				"type" : "float",
				"values" : ["uni", 80, 1000, "exp10"],
				"wrap" : 0,
				"default" : 0.5
			},
			{
				"name" : "bass_mult",
				"type" : "float",
				"values" : ["uni", 0, 4, "exp"],
				"wrap" : 0,
				"default" : 0.5
			},
			{
				"name" : "modulation_amount",
				"type" : "float",
				"values" : ["uni", 0, 1, "lin"],
				"wrap" : 0,
				"default" : 0.25
			},
			{
				"name" : "mix",
				"type" : "float",
				"values" : ["uni", 0, 1, "lin"],
				"wrap" : 0,
				"default" : 0.5
			}
		]
	}
}